Workbook

Sheet 全体設計
A1: Threads×Note 30日 バズ設計シート｜全体設計
A2: 自己分析・ChatGPT分析・競合バズ投稿（ユーザー提供）をもとに作成。黄色セルは運用しながら書き換える入力欄です。
A4: ■ コンセプト
A5: 1行コンセプト | B5: 副業と独立に約800万円使っても脱サラできなかった60代が、PC苦手からAI×Threadsで初収益を目指し、同じ副業迷子と一緒に再挑戦する実録。
A6: キャッチコピー | B6: 60代、まだ稼げてない。でも、もう遠回りはしない。
A7: 立ち位置 | B7: 先生ではなく「同じ副業迷子の一歩先を歩く人」。成功談ではなく、失敗の地図と次の一歩を渡す。
A8: ターゲット | B8: PCが苦手な50〜60代。①副業したいが一歩を踏み出せない人 ②何度も副業に失敗したが諦めきれず、今度こそ成果を出したい人
A9: フロント商品 | B9: Note「50代・60代のための副業迷子脱出ロードマップ」980〜2,980円（まずは980円で検証→反応を見て価格・内容を調整）
A10: ■ プロフィール
A11: 名前欄 | B11: 60代からの副業やり直し日記｜PC苦手×AI
A12: プロフィール文 | B12: 副業と独立に約800万円使っても脱サラできなかった60代｜ブログ・物販・高額講座で遠回り｜小さい「ゃ」も打てなかった僕が、AI×Threadsで再挑戦中｜50〜60代の副業迷子へ、失敗談と小さな一歩を毎日共有｜↓遠回りを全部まとめたNote
A13: リンク | B13: Note「50代・60代のための副業迷子脱出ロードマップ」
A14: 固定投稿 | B14: Day1（800万円の自己紹介）を固定。プロフィールに来た人が最初に読む「物語の入口」にする。
A15: ■ 30日の狙い
A16: 目的 | B16: 毎日1本、拡散力のある投稿で認知を取り、プロフィール→Noteへ流す。浅い悩み多め（約7割）で間口を広げ、深い悩み（約3割）でファン化する。
A17: 配分（自動集計） | B17: ="浅い悩み："&COUNTIF(30日投稿スケジュール!$D$6:$D$35,"浅")&"本／深い悩み："&COUNTIF(30日投稿スケジュール!$D$6:$D$35,"深")&"本（浅い悩み比率 "&TEXT(COUNTIF(30日投稿スケジュール!$D$6:$D$35,"浅")/30,"0%")&"）" -> 浅い悩み：21本／深い悩み：9本（浅い悩み比率 70%）
A18: 週ごとのテーマ | B18: 1週目：認知（衝撃の事実・自己紹介）／2週目：共感（本音・家族）／3週目：信頼（実用・保存）／4週目：販売（Note導線強化・30日の振り返り）
A19: ■ 投稿ルール（全投稿共通）
A20: 冒頭 | B20: 1行目は20〜30字。「衝撃の事実（数字＋自分の失敗）」か「常識破壊（〜ではありません／〜は古い）」に振り切る。2行目で補強し、直後に1行空ける。
A21: 分割 | B21: 1投稿目は冒頭〜意外な原因まで。最後に「続きはツリーへ👇」か問いかけで切る。2投稿目（ツリー）に理由・対策・未来・導線を置く（jin_kasegupro型。1/2表示がタップを誘う）。
A22: リンクの置き方 | B22: Noteのリンクは本文に直接貼らず「プロフィールのNote」と書く。外部リンク付き投稿は表示が伸びにくいという声があるため（公式発表ではない）。リンクを貼る場合は、ツリーの最後か自分のリプ欄に貼って反応を比較する。
A23: 返信 | B23: 投稿後30〜60分は、来たコメントに全部返信する（mone_gooday型：作者の返信が会話を生み、表示が伸びる）。返信の中で自然にNoteを紹介するのはOK。
A24: 投稿時間（検証用の仮説） | B24: 平日20:30／土日7:30から開始。2週目以降は「効果測定」シートで反応の良い時間に寄せる。
A25: ■ 守ること（信頼を落とさないため）
A26: 800万円の表記 | B26: 清掃業の独立（フランチャイズ等で約400〜500万円）を含む総額。必ず「副業と独立に」「合計約」と書き、ネット副業の教材費だけで800万円と誤解されないようにする。
A27: 実績の書き方 | B27: まだ出ていない収益・販売数は書かない。「こんなに買われる」というスタンスは、実際の販売数が出たらDay16・Day30の冒頭に実数で入れる（例：「小さい『ゃ』も打てなかった60代のNoteが、初月で【 】部売れました」）。
A28: 会社名・人名 | B28: 過去に契約・解約したサービス名や講師名は出さない。「ある案件」「ある講座」と書く。
A29: 根拠のない権威づけ | B29: 競合の「脳科学でも証明されている」型は使わず、「30年日記を続けて分かった」など自分の体験を根拠にする。
A30: 年齢表記 | B30: このシートは「60代」で統一（ChatGPT分析の最終コンセプトに合わせた）。実年齢と違う場合は、全シートで「60代」を置換してください。
A31: Note公開前 | B31: Noteがまだ無い期間は、ツリー最後の一文を「フォローして続きを見届けてください」に差し替える。

Sheet 自己分析まとめ
A1: 自己分析まとめ｜投稿の材料になる実体験
A2: ユーザーの自己分析とChatGPTとのやり取りから抽出。投稿では事実の範囲内で使う（盛らない）。
A4: 区分 | B4: 素材（事実） | C4: 投稿での使い方 | D4: 使用Day | E4: 表現上の注意
A5: お金・失敗 | B5: 副業と独立に合計約800万円（清掃業FC約400〜500万円、コンサル6件×30〜40万円、SNS運用講座100万円、3万円前後の情報商材×約6） | C5: 最強の衝撃フック。固定投稿・節目の投稿だけで使う | D5: 1, 21, 24, 26, 30 | E5: 毎回使うと刺激頼みになる。内訳を聞かれたら正直に答える
A6: お金・失敗 | B6: ブログを2年。朝早く起き、夜1時まで。AIのない17〜18年前。成果は出ず | C6: 努力の量より場所、の根拠 | D6: 1, 19 | E6: 当時のコンサル名は出さない
A7: お金・失敗 | B7: eBay輸出は英語で挫折。カメラ転売は張り付きのリサーチ競争で継続できず | C7: 「苦手で戦うと続かない」の具体例 | D7: 7, 11, 19
A8: お金・失敗 | B8: 清掃業で独立→生活できず廃業。退去清掃を妻と両親に手伝ってもらった | C8: 家族への申し訳なさ、独立の怖さ | D8: 1, 19, 20
A9: お金・失敗 | B9: 最近もアフィリエイト案件をサポート不足で解約 | C9: 無料相談・契約前チェックの根拠 | D9: 22（冒頭案③） | E9: サービス名は出さない
A10: PC・AI | B10: 小さい「ゃ」「ゅ」の打ち方すら知らず、自分で調べて覚えた。ブログのおかげでタイピングができるようになった | C10: PC苦手層への最大の共感フック | D10: 2, 14
A11: PC・AI | B11: 聞く前にまず自分で調べ、「どこまでやったか」を申告してから質問する習慣 | C11: PC苦手でも前に進む方法として紹介 | D11: 2
A12: 仕事 | B12: 年齢を理由に8社に断られた。2ヶ月仕事がなかった | C12: 雇用不安・年齢の壁の投稿 | D12: 3 | E12: 「連続」とは書かない（事実の範囲で）
A13: 仕事 | B13: 化粧品工場の派遣。マスク・帽子・長袖で目しか出ない服装、夏は暑い。契約は12月末まで | C13: 生活が見える描写（yuko_insta_t型） | D13: 17 | E13: 勤務先が特定される情報は書かない
A14: 仕事 | B14: フォークリフトの運転技術で「正社員の人でしょ」と驚かれた | C14: 体はまだ動く＝年齢で落とされる悔しさ | D14: 3（冒頭案③）
A15: 仕事 | B15: ダスキン新宿営業所で新人部門1位（20代・東京8年） | C15: 「営業1位でもネットでは20年以上結果が出なかった」ギャップ | D15: 20（冒頭案③）
A16: 仕事 | B16: GS、製造、営業、清掃自営、介護、ビル管理、フォークリフト。職業訓練2回 | C16: 転職の多さ＝困りごとを知っている財産 | D16: 20
A17: 家族 | B17: 妻に「苦手な分野に行くから成果が出ない」と言われた。AIの本を買ってきたのは妻。相談会も最初は反対→「信用できる」と言ってくれた | C17: 家族の一言から始まる型（saori型） | D17: 11 | E17: 妻の言葉は実際の言葉に近づけて調整
A18: 家族 | B18: 兄は外資系企業で副社長まで。キャンピングカー所有。兄への金銭的コンプレックス | C18: 比較の苦しさ→昨日の自分と比べる | D18: 14 | E18: 兄の会社名は出さない
A19: 家族 | B19: 同級生：「あと10年はこの会社で」／自営の建築士は年金が不安 | C19: 同世代の焦り | D19: 14（冒頭案③）
A20: 家族 | B20: 修繕費・保険・娘の専門学校の学費が残る。妻と旅行に行きたい | C20: 稼ぎたい理由（等身大の夢） | D20: 23
A21: 強み | B21: 30年以上日記を継続（3年→5年→10年日記の3冊目）。見返して助けられた経験が3〜4回 | C21: 継続・記録の権威づけ（mone_gooday型の「根拠」を自分の体験に置き換え） | D21: 6, 9, 25
A22: 強み | B22: サッカー：左ウイング。ラインを割るまで諦めない。中学で中国大会 | C22: 余韻型（320_reishi型）の物語 | D22: 28
A23: 価値観 | B23: 「言い訳をするのが一番嫌い。言い訳するなら別の方法を考える」 | C23: 一言引用型の名言として使う | D23: 3, 28
A24: 価値観 | B24: 人と比べず昨日の自分を超える／今日できることに集中 | C24: 比較・焦りの投稿の結論 | D24: 14
A25: 価値観 | B25: 講座は詐欺とは言えない。成果を出した人もいた。人のせいにしない | C25: 誠実さで信頼を取る逆張り | D25: 5, 26

Sheet 競合バズ分析
A1: 競合バズ分析｜反応の大きい投稿の要素と構造
A2: 数値はユーザー提供（Threads監視投稿：2026年10月8日時点／共有リンクの閲覧数表示）。他人の閲覧数は通常非公開のため「判定」は推定。
A4: 重要度 | B4: アカウント | C4: 投稿テーマ／冒頭 | D4: いいね | E4: 返信 | F4: 再投稿 | G4: 閲覧数（表示 or 判定） | H4: 刺さった要素 | I4: 構造の分解 | J4: コメント欄の傾向 | K4: 自分への転用（使う型） | L4: URL
A5: 最重要 | B5: saori.bihada.recipe | C5: 54歳・超アナログ・家族に笑われた | D5: 14800 | E5: 1100 | F5: 28 | G5: 5万以上が極めて濃厚（判定） | H5: 年齢、家族からの否定、悔しさ、再挑戦 | I5: 他者の一言→弱点の告白→それでも諦めない→読者への問い | J5: （ユーザー提供の範囲では未取得） | K5: C型：Day3（8社に断られた）、Day11（妻の一言）、Day14（兄との比較） | L5: https://www.threads.com/@saori.bihada.recipe/post/DMgqXnaT9bg
A6: 最重要 | B6: tomoyo_pc_web | C6: 50代女性はPCが苦手なのではなく… | D6: 385 | E6: 363 | F6: 5 | G6: 非公開 | H6: 「苦手」の定義を覆して読者を救う。返信数がいいねに近い＝語りたくなる | I6: 常識の否定（〜なのではなく）→本当の原因→読者の安堵 | J6: （未取得） | K6: D型：Day2、6、10、15、18、27（PC苦手層の救済） | L6: https://www.threads.com/@tomoyo_pc_web/post/DU7GwvLj7KU
A7: 高 | B7: hikari.mama.09 | C7: 50代になってバカになったのかと心配 | D7: 11000 | E7: 452 | F7: 14 | G7: 5万以上が極めて濃厚（判定） | H7: 人に言いにくい不安を短く告白 | I7: 短い告白→「これって私だけ？」→返信しやすい | J7: （未取得） | K7: E型：Day7、23、29（参加型） | L7: https://www.threads.com/@hikari.mama.09/post/DbeTVpmk9Mr
A8: 高 | B8: aigogo1701 | C8: AI副業は50代のほうが有利 | D8: 137 | E8: 29 | F8: 2 | G8: 非公開 | H8: 年齢の弱みを経験という強みに反転 | I8: 今さら無理を否定→人生経験を武器に変える | J8: （未取得） | K8: Day16、20（失敗・転職歴を強みに） | L8: https://www.threads.com/@aigogo1701/post/DSM-60nATHk
A9: 高 | B9: yuko_insta_t | C9: 60歳で朝2時間AI作業 | D9: 99 | E9: 31 | F9: 0 | G9: 非公開 | H9: 年齢・時間・過去の不安・途中成果 | I9: 生活が見える数字＋小さな進歩 | J9: （未取得） | K9: Day17（派遣の現場描写）、Day30（30日の数字公開） | L9: https://www.threads.com/@yuko_insta_t/post/DY-jMtdCfwk
A10: 中〜高 | B10: anata_mo_nihon_ichi | C10: 50代はもう時間がない | D10: 915 | E10: 61 | F10: 2 | G10: 5万以上の可能性あり（判定） | H10: 残り時間への焦り | I10: 焦り→今日やる小さな一歩 | J10: （未取得） | K10: Day8、13（小さく始める） | L10: https://www.threads.com/@anata_mo_nihon_ichi/post/DY_waRoEnld
A11: 中 | B11: sorakapu2710 | C11: 40〜50代で副業している人への質問 | D11: 37 | E11: 38 | F11: 0 | G11: 非公開 | H11: 回答しやすい市場調査型 | I11: 副業歴・失敗理由・月いくら欲しいかを聞く | J11: （未取得） | K11: Day7、22、23（質問でコメントを集め、悩みを収集） | L11: https://www.threads.com/@sorakapu2710/post/C8yQAR0SNij
A12: 最重要（構造） | B12: 320_reishi | C12: 後ろの人のためにドアを押さえる人、いますか？／祖母「そういう人は無自覚に徳を積んどるよ」 | G12: 132,890（表示） | H12: 誰でも「YES」と答えられる問い＋身近な人の一言＋自分を肯定できる結論。「、、、」の余韻 | I12: 問いかけ1行→身近な人の言葉の引用→余韻で切る（1/2）→2/2で意味づけ | J12: 「普通にやってる」「徳を積んでたんだ」と、自分の行動を語るコメントが大量。答えるハードルが極めて低い | K12: F型：Day28（ラインを割るまで）。問いは「誰でも答えられる」ものにする | L12: https://www.threads.com/@320_reishi/post/DW2nN5lig-z
A13: 最重要（構造） | B13: mone_gooday | C13: 脳科学でも証明されているけど、お気に入りのマグカップで…「好き」で埋め尽くせる人は豊かになる | G13: 277,918（表示） | H13: 権威づけの一言＋誰でも今日できる具体例3つ＋前向きな結論 | I13: 根拠1行→具体的な行動3つ→断定の結論（1/3） | J13: 作者がほぼ全コメントに返信し、会話が続いている。「実践中」「わかる」の共感が中心 | K13: G型：Day9、25。ただし根拠は「30年日記」など自分の体験に置き換える。全コメント返信を真似る | L13: https://www.threads.com/@mone_gooday/post/DT-Um6ZgX45
A14: 高（構造） | B14: jin_kasegupro | C14: 絶対に初心者が参入してはいけない副業ジャンル（物販・note・動画編集…） | G14: 20,581（表示） | H14: 「絶対に〜してはいけない」の断言＋リスト＋答えを次の投稿に持ち越す | I14: 断言→NGリスト→「狙いやすいのは、」で1/2を切る→2/2で答え→「努力量より、努力する場所」で締め | J14: （未取得） | K14: B型：Day4、12、19、21、24。答えをツリーに置いて、ツリー→プロフィールへの動線を作る | L14: https://www.threads.com/share/HIv4Hf-Yu/
A16: ■ 共通するバズ要素（10投稿から抽出）
A17: ① 1行目で「自分ごと」になる：年齢・家族・PC苦手など、読者の属性をそのまま入れる（saori・tomoyo・hikari）
A18: ② 答えるハードルが低い問い：YES/NOや自分の体験で答えられる（320_reishi・sorakapu）。返信が多い投稿ほど表示が伸びやすい傾向
A19: ③ 常識の否定で読者を救う：「〜なのではなく、〜なだけ」（tomoyo）。責められず、救われる側に立てる
A20: ④ 続きを持ち越す：1/2で答えを言わずに切る（jin・320_reishi・mone）。ツリーを開く＝滞在時間が伸び、プロフィールを見る人が増える
A21: ⑤ 作者の返信で会話を続ける（mone_gooday）
A22: ⑥ 誇張した権威づけ（脳科学で証明 等）は避け、自分の実体験（800万円・8社・30年日記）を「根拠」にする

Sheet 構造テンプレート
A1: 文章構造テンプレート｜基本型と、プロフィール遷移が起きる別の順番
A2: A型はご指定の流れ。B〜G型は競合バズ投稿から逆算した「別の順番」。使用Dayは30日投稿スケジュールから自動集計。
A4: 型 | B4: 名前 | C4: 参考にしたバズ投稿 | D4: 文章の順番 | E4: プロフィールクリックが起きる理由 | F4: 向いている悩み | G4: 使用回数 | H4: 注意点
A5: A | B5: 基本型（7ステップ・2投稿分割） | C5: jin_kasegupro＋saori（2投稿に分割） | D5: 1. 強い冒頭（衝撃の事実／常識破壊） 2. 50〜60代の副業迷子が困っている具体的な場面 3. 常識の否定・意外な原因 ―― ここで1投稿目を切る（続きはツリーへ👇）―― 4. 専門家ではないが、一歩先を行く副業迷子だから言える理由 5. 今すぐできる対策1〜5個 6. 家族や自分に起きる未来の変化 7. 続きを読む・フォロー・Noteへの導線 | E5: 対策で「役に立った」と感じた直後に、「もっと知りたい」の受け皿としてNoteを置くため | F5: 高額講座・副業選び・時間・不安全般 | G5: =COUNTIF(30日投稿スケジュール!$F$6:$F$35,A5) -> 8 | H5: 1投稿に全部入れると長く、読了率が落ちる。必ず3と4の間で分割する
A6: B | B6: 断言リスト→引き型 | C6: jin_kasegupro（20,581表示） | D6: 1. 断言の冒頭（「〜してはいけない」「苦労しやすい〜」） 2. NGリスト3〜5個（自分の失敗を括弧書きで） 3. 「では、何をすればいいのか。」で1投稿目を切る ―― ツリー ―― 4. 答えを1行で 5. 理由3つ 6. 名言風の締め（例：頑張る量より、頑張る場所） 7. 導線 | E6: 答えを知るためにツリーを開く→答えが「この人の進め方」なので、そのままプロフィールを見に行く | F6: 副業選び・AIの使い方・スマホ副業 | G6: =COUNTIF(30日投稿スケジュール!$F$6:$F$35,A6) -> 5 | H6: NGリストで他人の副業を否定しすぎない。「稼いでいる人もいる」と一言添える
A7: C | B7: 他者の一言→悔しさ→問い型 | C7: saori.bihada.recipe（いいね14,800） | D7: 1. 他者の一言、または自分が受けた仕打ち（年齢で8社・妻の一言・兄との差） 2. 自分の弱点を正直に告白 3. 悔しさ 4. それでも諦めない理由と宣言 5. 読者への問い（「〜したことはありますか？」） ―― ツリー ―― 6. 今の挑戦の報告＋フォロー導線（Noteは軽く） | E7: 対策ではなく「この人がどうなるか見届けたい」という人物への興味でプロフィールを見る | F7: 年齢・家族・比較などの深い悩み | G7: =COUNTIF(30日投稿スケジュール!$F$6:$F$35,A7) -> 3 | H7: Noteを強く売らない。フォロー優先。返信には必ず返す
A8: D | B8: 再定義救済型 | C8: tomoyo_pc_web（返信363） | D8: 1. 「〇〇なのは△△のせいではありません」（読者の自責を否定） 2. 読者が困っている場面 3. 本当の原因（「教わっていないだけ」） ―― ツリー ―― 4. 自分も同じだった話 5. 今日からの対策 6. 「保存して見返してください」＋Note導線 | E8: 責められずに救われた安心感→この人なら分かってくれる、で他の投稿とNoteを見に来る | F8: PC操作・AIが難しい・投稿が伸びない | G8: =COUNTIF(30日投稿スケジュール!$F$6:$F$35,A8) -> 8 | H8: 読者を「苦手な人」と決めつけない言い回しにする
A9: E | B9: 告白＋「私だけ？」型 | C9: hikari.mama.09（いいね11,000）／sorakapu2710 | D9: 1. 短い告白（3〜6行） 2. 「これって僕だけですか？」 3. 答えやすい質問（選択肢があると◎） ―― ツリー（任意）―― 4. 「全部読みます」＋返信した人への一言 5. 返信の中でNoteを自然に紹介 | E9: コメントへの作者の返信が通知で届き、そこからプロフィールに来る（本文より返信欄が導線） | F9: 続かない・孤独・夢・悩み収集 | G9: =COUNTIF(30日投稿スケジュール!$F$6:$F$35,A9) -> 3 | H9: 本文は短く。投稿後1時間はコメントに張り付いて返信する
A10: F | B10: 一言引用→余韻型 | C10: 320_reishi（132,890表示） | D10: 1. 誰でも答えられる問い、または心に残る一言の引用 2. その言葉をくれた人（自分の過去・家族・サッカー） 3. 余韻（「、、、」で切る） ―― ツリー ―― 4. その言葉の意味を今の自分に重ねる 5. 読者へのエール＋フォロー導線 | E10: 物語に共感した人が「どんな人なんだろう」とプロフィールを見る。再投稿されやすい | F10: 一歩が踏み出せない・諦めかけている | G10: =COUNTIF(30日投稿スケジュール!$F$6:$F$35,A10) -> 1 | H10: 説教くさくしない。具体的なノウハウは入れない
A11: G | B11: 一行の根拠→具体3つ→結論型 | C11: mone_gooday（277,918表示） | D11: 1. 根拠の一行（「30年日記を続けて分かった」など自分の体験） 2. 誰でも今日できる具体的な行動3つ 3. 断定の結論 ―― ツリー ―― 4. 自分の実例 5. Note導線 | E11: すぐ真似できる行動を保存した人が、他のノウハウも探してプロフィールへ | F11: 時間がない・続かない | G11: =COUNTIF(30日投稿スケジュール!$F$6:$F$35,A11) -> 2 | H11: 「脳科学で証明」など、確認できない権威は使わない
A13: ■ 冒頭（1〜2行目）の型｜衝撃の事実と常識破壊に振り切る
A14: 種類 | B14: 型 | C14: 例（このシートの投稿から）
A15: 衝撃の事実 | B15: ［数字］＋［自分の失敗］ | C15: 副業と独立に、合計約800万円使いました。それでも60代の今、まだ脱サラできていません。
A16: 衝撃の事実 | B16: ［他者の仕打ち］＋［でも体は動く］ | C16: 年齢を理由に断られた会社、8社。体は、まだちゃんと動くのに。
A17: 衝撃の事実 | B17: ［意外なギャップ］ | C17: 兄は外資系企業で副社長まで上り詰めた人。弟の僕は、60代の派遣社員です。
A18: 常識破壊 | B18: 〇〇なのは△△のせいではありません | C18: 60代がパソコンを苦手なのは、才能のせいではありません。誰にも「打ち方」を教わっていないだけです。
A19: 常識破壊 | B19: 〇〇は、もう昔の話です | C19: 「パソコンがないと副業できない」は、もう昔の話です。
A20: 常識破壊 | B20: 〇〇するほど、××になる／〇〇は××ではありません | C20: 副業のYouTubeを見ている時間は、副業ではありません。
A21: 常識破壊 | B21: 最初にしてはいけない〇〇 | C21: AI初心者がChatGPTに最初にしてはいけない質問。「稼げる副業を教えて」。

Sheet 悩みリスト
A1: ターゲットの悩みリスト｜浅い悩み・深い悩み
A2: ChatGPT分析の40項目＋今回追加分。使用Dayは30日投稿スケジュールの割り当て。コメントで集まった悩みは下に追記していく。
A4: 区分 | B4: No. | C4: 悩み | D4: 刺さりやすい投稿テーマ | E4: 使用Day
A5: 浅い悩み | B5: 1 | C5: PCで文字入力が遅い | D5: 小さい「ゃ」の打ち方 | E5: 2
A6: 浅い悩み | B6: 2 | C6: AIの始め方が分からない | D6: ChatGPTの最初の質問 | E6: 4
A7: 浅い悩み | B7: 3 | C7: Threadsの使い方が分からない | D7: 初投稿までの手順 | E7: （次の30日）
A8: 浅い悩み | B8: 4 | C8: 何を投稿すればいいか分からない | D8: 体験談を投稿に変える | E8: 6
A9: 浅い悩み | B9: 5 | C9: 副業の種類が多すぎる | D9: 副業選びの比較 | E9: 13, 19
A10: 浅い悩み | B10: 6 | C10: 無料と有料の違いが分からない | D10: AI無料版で試すこと | E10: （次の30日）
A11: 浅い悩み | B11: 7 | C11: スマホだけで副業できるか不安 | D11: スマホでできる作業 | E11: 12
A12: 浅い悩み | B12: 8 | C12: 毎日投稿するネタがない | D12: 失敗経験からネタ出し | E12: 6
A13: 浅い悩み | B13: 9 | C13: noteの作り方が分からない | D13: 初心者向けnote作成 | E13: 16
A14: 浅い悩み | B14: 10 | C14: フォロワーが増えない | D14: 投稿改善の実験記録 | E14: 15
A15: 浅い悩み | B15: 11 | C15: 投稿に反応がつかない | D15: 冒頭1行の改善 | E15: 15
A16: 浅い悩み | B16: 12 | C16: どの教材を選べばいいか分からない | D16: 購入前チェック | E16: 5
... A50: 深い悩み | B50: 20 | C50: 最後に一度、自分の力で稼ぎたい | D50: 初収益への挑戦 | E50: 30
A56: ↑黄色の行：コメントで集まった悩みを追記（次の30日の企画に使う）

Sheet 30日投稿スケジュール
A1: 30日投稿スケジュール｜冒頭案3つ＋本文＋ツリー
A2: 開始日 | B2: 46307 | C2: 使い方：①B2に開始日 ②「採用する冒頭」で1〜3を選ぶ→「1投稿目コピペ用」が自動で切り替わる ③1投稿目→ツリー（2投稿目）の順に投稿。文字数はThreadsの上限500字以内か自動チェック。黄色セル＝入力欄。
C3: 【 】は投稿前に実数へ書き換える箇所。冒頭案①＝衝撃の事実寄り／②＝常識破壊寄り／③＝別角度（どれも本文につながるように作成）。
A5: Day | B5: 日付 | C5: 曜日 | D5: 悩み区分 | E5: フェーズ | F5: 構造型 | G5: 構造名 | H5: 狙う悩み | I5: 投稿テーマ | J5: 参考バズ投稿 | K5: 冒頭案① | L5: 冒頭案② | M5: 冒頭案③ | N5: 採用する冒頭 | O5: 本文（冒頭の続き） | P5: 1投稿目コピペ用（自動） | Q5: 1投稿目 文字数 | R5: ツリー（2投稿目）理由・対策・未来・導線 | S5: ツリー 文字数 | T5: 返信を生む問い | U5: 狙う指標 | V5: 投稿時間（仮説）
A6: 1 | B6: =$B$2+A6-1 -> 46307 | C6: =CHOOSE(WEEKDAY(B6),"日","月","火","水","木","金","土") -> 月 | D6: 浅 | E6: 1週目：認知（衝撃・自己紹介） | F6: A | G6: 基本型（7ステップ・2投稿分割） | H6: どの副業を選べばいいか分からない／高額講座に手を出しがち | I6: 副業と独立に約800万円使った60代の自己紹介（固定投稿にする） | J6: saori.bihada.recipe（年齢×悔しさ）＋jin_kasegupro（1/2で切る） | K6: 副業と独立に、合計約800万円使いました。 それでも60代の今、まだ脱サラできていません。 | L6: 「副業は自己投資が大事」。 この言葉を信じて、約800万円を使った60代です。 | M6: コンサルを6件受けた僕が断言します。 副業迷子の原因は「知識不足」じゃありません。 | N6: 1 | O6: ブログは2年。朝早く起きて、夜は1時まで書きました。 アフィリエイト、メルマガ、eBay輸出、カメラ転売。 清掃業で独立して、廃業したこともあります。 「次こそは」と申し込みボタンを押すたびに、 妻の顔が浮かびました。 でも、うまくいかなかった原因は 才能でも、年齢でもなかった。 「自分に合うか」を確かめる前に、 お金を払っていたことです。 （続きはツリーへ👇） | P6: =CHOOSE(N6,K6,L6,M6)&CHAR(10)&CHAR(10)&O6 -> 副業と独立に、合計約800万円使いました。 それでも60代の今、まだ脱サラできていません。 ブログは2年。朝早く起きて、夜は1時まで書きました。 アフィリエイト、メルマガ、eBay輸出、カメラ転売。 清掃業で独立して、廃業したこともあります。 「次こそは」と申し込みボタンを押すたびに、 妻の顔が浮かびました。 でも、うまくいかなかった原因は 才能でも、年齢でもなかった。 「自分に合うか」を確かめる前に、 お金を払っていたことです。 （続きはツリーへ👇） | Q6: =LEN(P6) -> 233 | R6: 成功者じゃない僕が、これだけは言えます。 同じ失敗を、全部自分の財布で試したからです。 講座を探す前に、この3つだけやってください。 ①平日に使える時間を「分」で書き出す ②英語・PC・体力など、苦手を3つ書く ③1万円以上の申し込みは48時間寝かせる これを知っていれば、遠回りの半分は避けられたと思っています。 家族に心配をかけない副業選びを。 僕の800万円の遠回りは、プロフィールのNoteに全部まとめました。 同じ副業迷子の方、フォローして一緒に抜け出しましょう。 | S6: =LEN(R6) -> 241 | T6: あなたが一番お金を使った副業は何ですか？ | U6: 認知・プロフィール遷移（固定投稿） | V6: =IF(OR(C6="土",C6="日"),"7:30","20:30") -> 20:30
A7: 2 | B7: =$B$2+A7-1 -> 46308 | C7: =CHOOSE(WEEKDAY(B7),"日","月","火","水","木","金","土") -> 火 | D7: 浅 | E7: 1週目：認知（衝撃・自己紹介） | F7: D | G7: 再定義救済型 | H7: PCで文字入力が遅い・小さい文字が打てない | I7: 小さい「ゃ」も打てなかった僕のPC入門 | J7: tomoyo_pc_web（苦手ではなく教わっていないだけ） | K7: ブログを始めた40代の頃、 僕は小さい「ゃ」の打ち方すら知りませんでした。 | L7: 60代がパソコンを苦手なのは、才能のせいではありません。 誰にも「打ち方」を教わっていないだけです。 | M7: キーボードが打てなくても大丈夫。 今はAIに「話しかけるだけ」で副業の準備ができます。 | N7: 2 | O7: 「しゃ」「きょ」が打てない。 「@」がどこにあるか分からない。 家族に聞くのも、なんだか気まずい。 僕もそうでした。 小さい文字を1つずつ検索して、やっと覚えました。 できなかった理由は単純です。 学校でも会社でも、誰も教えてくれなかった。 苦手なんじゃなくて「知らなかった」だけなんです。 （今日から使える方法はツリーへ👇） | P7: =CHOOSE(N7,K7,L7,M7)&CHAR(10)&CHAR(10)&O7 -> 60代がパソコンを苦手なのは、才能のせいではありません。 誰にも「打ち方」を教わっていないだけです。 「しゃ」「きょ」が打てない。 「@」がどこにあるか分からない。 家族に聞くのも、なんだか気まずい。 僕もそうでした。 小さい文字を1つずつ検索して、やっと覚えました。 できなかった理由は単純です。 学校でも会社でも、誰も教えてくれなかった。 苦手なんじゃなくて「知らなかった」だけなんです。 （今日から使える方法はツリーへ👇） | Q7: =LEN(P7) -> 218 | R7: PCが超苦手だった僕が、遠回りして覚えたこと。 ①小さい文字は「L」か「X」を先に打つ（L→Y→Aで「ゃ」） ②スマホなら音声入力でOK。マイクを押して話すだけ ③分からない操作は「やりたいこと＋やり方」で検索 ④それでも分からなければ「ここまでやった」を添えて人に聞く 文字が打てるようになると、 家族に聞く回数が減って、自分で調べる楽しさが戻ってきます。 PC苦手な60代のための「最初の一歩」は、プロフィールのNoteに。 フォローして、一緒にゆっくり進みましょう。 | S7: =LEN(R7) -> 239 | T7: パソコンで一番困っている操作は何ですか？ | U7: 共感・保存・返信 | V7: =IF(OR(C7="土",C7="日"),"7:30","20:30") -> 20:30
A8: 3 | B8: =$B$2+A8-1 -> 46309 | C8: =CHOOSE(WEEKDAY(B8),"日","月","火","水","木","金","土") -> 水 | D8: 深 | E8: 1週目：認知（衝撃・自己紹介） | F8: C | G8: 他者の一言→悔しさ→問い型 | H8: もう年齢的に手遅れではないか／雇用の不安 | I8: 年齢で8社に断られた日 | J8: saori.bihada.recipe（他者の否定→悔しさ→それでも→問い） | K8: 年齢を理由に断られた会社、8社。 体は、まだちゃんと動くのに。 | L8: 60代の最大の敵は、体力じゃない。 履歴書に書く「年齢の数字」です。 | M8: フォークリフトを運転すれば、正社員と間違えられる。 それでも、書類では年齢で落とされます。 | N8: 1 | O8: 仕事がない2ヶ月間。 面接に行っては、断られて帰る日々でした。 悔しかった。 「なんで、体は動くのに」と何度も思いました。 でも、言い訳だけはしたくなかった。 言い訳をするくらいなら、別の方法を考える。 だから決めました。 会社だけに、人生を預けるのはやめる。 今は派遣で働きながら、 AIとThreadsで、もう一度挑戦しています。 年齢を理由に、何かを諦めかけたことはありますか？ | P8: =CHOOSE(N8,K8,L8,M8)&CHAR(10)&CHAR(10)&O8 -> 年齢を理由に断られた会社、8社。 体は、まだちゃんと動くのに。 仕事がない2ヶ月間。 面接に行っては、断られて帰る日々でした。 悔しかった。 「なんで、体は動くのに」と何度も思いました。 でも、言い訳だけはしたくなかった。 言い訳をするくらいなら、別の方法を考える。 だから決めました。 会社だけに、人生を預けるのはやめる。 今は派遣で働きながら、 AIとThreadsで、もう一度挑戦しています。 年齢を理由に、何かを諦めかけたことはありますか？ | Q8: =LEN(P8) -> 230 | R8: 成功者ではありません。まだ挑戦の途中です。 だからこそ、年齢で落とされた悔しさも、 そこから立ち上がる過程も、全部ここに書いていきます。 同じように「もう遅いのかな」と思っている50代・60代の方。 フォローして、一緒に見届けてください。 プロフィールのNoteには、年齢の壁にぶつかってから 副業を選び直した手順をまとめています。 | S8: =LEN(R8) -> 168 | T8: 年齢を理由に、何かを諦めかけたことはありますか？ | U8: 共感・返信・フォロー | V8: =IF(OR(C8="土",C8="日"),"7:30","20:30") -> 20:30
A9: 4 | B9: =$B$2+A9-1 -> 46310 | C9: =CHOOSE(WEEKDAY(B9),"日","月","火","水","木","金","土") -> 木 | D9: 浅 | E9: 1週目：認知（衝撃・自己紹介） | F9: B | G9: 断言リスト→引き型 | H9: AIの始め方・何を聞けばいいか分からない | I9: ChatGPTに最初にしてはいけない質問 | J9: jin_kasegupro（NGリスト→1/2で切る→2/2で答え） | K9: AI初心者がChatGPTに最初にしてはいけない質問。 「稼げる副業を教えて」。 | L9: AIは「検索窓」じゃありません。 60代が使うなら「相談相手」です。 | M9: AIを使っても答えがピンとこないのは、 AIじゃなく「聞き方」の問題です。 | N9: 1 | O9: 同じ理由で、避けたい質問はこちら。 ・おすすめの副業は？ ・簡単に稼ぐ方法は？ ・ブログの書き方を教えて どれも、誰が聞いても同じ答えが返ってきます。 あなたの年齢も、時間も、苦手も、AIは知らないから。 では、最初に何を聞けばいいのか。 | P9: =CHOOSE(N9,K9,L9,M9)&CHAR(10)&CHAR(10)&O9 -> AI初心者がChatGPTに最初にしてはいけない質問。 「稼げる副業を教えて」。 同じ理由で、避けたい質問はこちら。 ・おすすめの副業は？ ・簡単に稼ぐ方法は？ ・ブログの書き方を教えて どれも、誰が聞いても同じ答えが返ってきます。 あなたの年齢も、時間も、苦手も、AIは知らないから。 では、最初に何を聞けばいいのか。 | Q9: =LEN(P9) -> 164 | R9: 答えは「自分のことを先に話す」です。 たとえば、こう聞いてみてください。 「私は60代、パソコンは苦手です。 平日に使えるのは1日30分、使えるお金は月5千円まで。 この条件で、向いている副業を3つ、 中学生にも分かる言葉で、理由付きで教えてください」 条件を渡すほど、AIは「あなた専用」の相談相手になります。 僕が使っている質問の型は、プロフィールのNoteにまとめました。 保存して、今夜1回だけ試してみてください。 | S9: =LEN(R9) -> 214 | T9: AIに聞いてみたいこと、コメントで教えてください | U9: 保存・ツリー遷移 | V9: =IF(OR(C9="土",C9="日"),"7:30","20:30") -> 20:30
A10: 5 | B10: =$B$2+A10-1 -> 46311 | C10: =CHOOSE(WEEKDAY(B10),"日","月","火","水","木","金","土") -> 金 | D10: 浅 | E10: 1週目：認知（衝撃・自己紹介） | F10: A | G10: 基本型（7ステップ・2投稿分割） | H10: 高額講座が必要か迷う・どの教材を選べばいいか | I10: コンサル6件受けて分かった、申し込む前のチェック | J10: aigogo1701（弱み→強みの反転） | K10: コンサルを6件受けて分かりました。 高額講座で稼げるかどうかは「申し込む前」にほぼ決まっています。 | L10: 「残りわずか」「今だけ価格」。 その講座、たいてい今じゃなくても大丈夫です。 | M10: 講座選びで一番大事なのは、 講師の実績ではありません。 | N10: 1 | O10: 夜中にセミナー動画を見て、 「この人についていけば変われるかも」と胸が熱くなる。 気づけば、カード番号を入力している。 僕は、これを何度も繰り返しました。 でも、講座が悪かったとは思っていません。 実際に、同じ講座で成果を出した人もいました。 合っていなかったのは、 講座の中身と「僕の時間と苦手」でした。 （申し込む前のチェックはツリーへ👇） | P10: =CHOOSE(N10,K10,L10,M10)&CHAR(10)&CHAR(10)&O10 -> コンサルを6件受けて分かりました。 高額講座で稼げるかどうかは「申し込む前」にほぼ決まっています。 夜中にセミナー動画を見て、 「この人についていけば変われるかも」と胸が熱くなる。 気づけば、カード番号を入力している。 僕は、これを何度も繰り返しました。 でも、講座が悪かったとは思っていません。 実際に、同じ講座で成果を出した人もいました。 合っていなかったのは、 講座の中身と「僕の時間と苦手」でした。 （申し込む前のチェックはツリーへ👇） | Q10: =LEN(P10) -> 227 | R10: 6件受けた僕が、今なら必ず確認すること。 ①1週間に何時間の作業が必要か ②サポートの回数と期間（書面で） ③自分の苦手な作業が入っていないか ④返金・解約の条件 ⑤一晩、家族に話してから決める これだけで「こんなはずじゃなかった」はかなり減ります。 家族に隠しごとをしない副業は、続きます。 講座を選ぶ前の全チェック項目は、プロフィールのNoteにまとめています。 | S10: =LEN(R10) -> 186 | T10: 講座に申し込んで後悔したこと、ありますか？ | U10: 保存・Note関心 | V10: =IF(OR(C10="土",C10="日"),"7:30","20:30") -> 20:30
A11: 6 | B11: =$B$2+A11-1 -> 46312 | C11: =CHOOSE(WEEKDAY(B11),"日","月","火","水","木","金","土") -> 土 | D11: 浅 | E11: 1週目：認知（衝撃・自己紹介） | F11: D | G11: 再定義救済型 | H11: 何を投稿すればいいか分からない・ネタがない | I11: 30年の日記と、60代のネタの掘り出し方 | J11: tomoyo_pc_web（再定義救済） | K11: 30年以上、日記を書き続けてきました。 それが今、副業でいちばんの武器になっています。 | L11: 「発信するネタがない」という60代ほど、 実はネタを一番持っています。 | M11: 失敗談は、恥ではありません。 誰かにとっての「地図」です。 | N11: 2 | O11: 「若い人みたいに、おしゃれな話はできない」 「人に教えられることなんて、何もない」 スマホを開いても、何を書けばいいか分からない。 でも、60年分の毎日の中に、ネタは全部あります。 転職、子育て、介護、失敗した副業。 同じ悩みを持つ人にとって、 それは教科書より役に立つ「本物の体験」です。 （ネタの掘り出し方はツリーへ👇） | P11: =CHOOSE(N11,K11,L11,M11)&CHAR(10)&CHAR(10)&O11 -> 「発信するネタがない」という60代ほど、 実はネタを一番持っています。 「若い人みたいに、おしゃれな話はできない」 「人に教えられることなんて、何もない」 スマホを開いても、何を書けばいいか分からない。 でも、60年分の毎日の中に、ネタは全部あります。 転職、子育て、介護、失敗した副業。 同じ悩みを持つ人にとって、 それは教科書より役に立つ「本物の体験」です。 （ネタの掘り出し方はツリーへ👇） | Q11: =LEN(P11) -> 203 | R11: 僕は3年日記から始めて、今は10年日記の3冊目です。 見返して「あの時こうだった」と助けられたことが何度もあります。 ネタの掘り出し方は3つ。 ①今までの仕事を全部書き出す ②一番悔しかった出来事を1つ書く ③それをAIに渡して「この体験から投稿ネタを5つ」と聞く あなたの遠回りは、誰かの近道になります。 体験を投稿とNoteに変える手順は、プロフィールのNoteに載せています。 | S11: =LEN(R11) -> 195 | T11: あなたが一番長く続けていることは何ですか？ | U11: 保存・フォロー | V11: =IF(OR(C11="土",C11="日"),"7:30","20:30") -> 7:30
A12: 7 | B12: =$B$2+A12-1 -> 46313 | C12: =CHOOSE(WEEKDAY(B12),"日","月","火","水","木","金","土") -> 日 | D12: 浅 | E12: 1週目：認知（衝撃・自己紹介） | F12: E | G12: 告白＋「私だけ？」型 | H12: 副業を始めては辞めてしまう | I12: 副業、何回やめましたか？（参加型） | J12: hikari.mama.09（短い告白＋私だけ？）／sorakapu2710（質問型） | K12: 副業、何回やめましたか？ 僕は、途中で数えるのをやめました。 | L12: 三日坊主じゃありません。 僕は「三ヶ月坊主」でした。 | M12: 副業をやめた回数＝失敗の回数、 ではないと思っています。 | N12: 1 | O12: ブログ、アフィリエイト、メルマガ。 eBay輸出、カメラ転売。 2〜3ヶ月でやめてしまったものもあります。 やめるたびに「また続かなかった」と落ち込んで、 しばらくして、また次を探していました。 これって、僕だけですか？ あなたが挫折した副業、コメントで教えてください。 全部読みます。 | P12: =CHOOSE(N12,K12,L12,M12)&CHAR(10)&CHAR(10)&O12 -> 副業、何回やめましたか？ 僕は、途中で数えるのをやめました。 ブログ、アフィリエイト、メルマガ。 eBay輸出、カメラ転売。 2〜3ヶ月でやめてしまったものもあります。 やめるたびに「また続かなかった」と落ち込んで、 しばらくして、また次を探していました。 これって、僕だけですか？ あなたが挫折した副業、コメントで教えてください。 全部読みます。 | Q12: =LEN(P12) -> 179 | R12: コメントをくれた方には、僕の経験から一言ずつ返します。 やめた副業の数だけ、 「自分に合わないもの」が分かってきたはずです。 合わないものを消していくと、最後に残るものがあります。 その消し方は、プロフィールのNoteにまとめました。 | S12: =LEN(R12) -> 120 | T12: あなたが挫折した副業は何ですか？ | U12: 返信数（悩み収集） | V12: =IF(OR(C12="土",C12="日"),"7:30","20:30") -> 7:30
A13: 8 | B13: =$B$2+A13-1 -> 46314 | C13: =CHOOSE(WEEKDAY(B13),"日","月","火","水","木","金","土") -> 月 | D13: 深 | E13: 2週目：共感（本音・家族） | F13: A | G13: 基本型（7ステップ・2投稿分割） | H13: また副業に失敗したら立ち直れない | I13: 怖いのはお金より「自分にがっかりすること」 | J13: anata_mo_nihon_ichi（焦り→今日の小さな一歩） | K13: 副業でいちばん怖いのは、お金を失うことじゃありません。 「また自分にがっかりすること」です。 | L13: 何度も失敗した人ほど、 次は「小さく」始めた方が強い。 | M13: 60代の再挑戦に、気合いはいりません。 | N13: 1 | O13: 申し込むたびに「今度こそ」と思う。 成果が出ない月の夜、通帳を見てため息をつく。 家族には「大丈夫」と言いながら、 本当は自分が一番、自分を信じられなくなっている。 僕も、何度もそうなりました。 でも、怖さの正体は失敗そのものじゃなかった。 「取り返しのつかない大きさ」で挑戦していたことです。 （小さく始める方法はツリーへ👇） | P13: =CHOOSE(N13,K13,L13,M13)&CHAR(10)&CHAR(10)&O13 -> 副業でいちばん怖いのは、お金を失うことじゃありません。 「また自分にがっかりすること」です。 申し込むたびに「今度こそ」と思う。 成果が出ない月の夜、通帳を見てため息をつく。 家族には「大丈夫」と言いながら、 本当は自分が一番、自分を信じられなくなっている。 僕も、何度もそうなりました。 でも、怖さの正体は失敗そのものじゃなかった。 「取り返しのつかない大きさ」で挑戦していたことです。 （小さく始める方法はツリーへ👇） | Q13: =LEN(P13) -> 216 | R13: 失敗を重ねた僕が、今やっている始め方です。 ①使うお金の上限を、先に紙に書く ②1日15分だけ、と決める ③30日でいったん判定する ④毎日1行、記録を残す 小さく始めれば、うまくいかなくても 「次はこう直そう」で終われます。 もう一度、自分を信じるところからやり直しませんか。 僕の再挑戦の手順は、プロフィールのNoteにあります。 | S13: =LEN(R13) -> 171 | T13: 今、副業で一番怖いことは何ですか？ | U13: 共感・フォロー | V13: =IF(OR(C13="土",C13="日"),"7:30","20:30") -> 20:30
A14: 9 | B14: =$B$2+A14-1 -> 46315 | C14: =CHOOSE(WEEKDAY(B14),"日","月","火","水","木","金","土") -> 火 | D14: 浅 | E14: 2週目：共感（本音・家族） | F14: G | G14: 一行の根拠→具体3つ→結論型 | H14: 副業の時間が取れない | I14: 時間を作らず、習慣に「くっつける」 | J14: mone_gooday（一行の権威→具体3つ→結論） | K14: 30年以上日記を続けてきて分かったこと。 続く人は「時間」ではなく「タイミング」を決めています。 | L14: 副業の時間は「作る」ものじゃありません。 もうある習慣に「乗せる」ものです。 | M14: 仕事終わりに副業ができないのは、 意志が弱いからではありません。 | N14: 2 | O14: 立ち仕事を終えて家に帰る。 ごはんを食べたら、もう何もしたくない。 「明日こそ」と思って、スマホを見て寝てしまう。 当然です。 疲れた体で「新しい時間」を作ろうとするから続かない。 夕食後のお茶、寝る前の歯みがき、通勤の時間。 すでに毎日やっていることの「後ろ」に、 15分だけくっつける。 それだけで、副業は生活の一部になります。 | P14: =CHOOSE(N14,K14,L14,M14)&CHAR(10)&CHAR(10)&O14 -> 副業の時間は「作る」ものじゃありません。 もうある習慣に「乗せる」ものです。 立ち仕事を終えて家に帰る。 ごはんを食べたら、もう何もしたくない。 「明日こそ」と思って、スマホを見て寝てしまう。 当然です。 疲れた体で「新しい時間」を作ろうとするから続かない。 夕食後のお茶、寝る前の歯みがき、通勤の時間。 すでに毎日やっていることの「後ろ」に、 15分だけくっつける。 それだけで、副業は生活の一部になります。 | Q14: =LEN(P14) -> 209 | R14: たとえば、こんなくっつけ方です。 ・朝のコーヒーの後 → AIに投稿ネタを3つ聞く ・昼休み → スマホで下書きを1つ ・夜の日記の前 → 投稿の反応を1行メモ 大きな時間はいりません。 続く人は、時間がある人ではなく、仕組みがある人です。 60代の副業スケジュール例は、プロフィールのNoteに。 | S14: =LEN(R14) -> 152 | T14: 毎日必ずやっている習慣は何ですか？ | U14: 保存・共感 | V14: =IF(OR(C14="土",C14="日"),"7:30","20:30") -> 20:30
A15: 10 | B15: =$B$2+A15-1 -> 46316 | C15: =CHOOSE(WEEKDAY(B15),"日","月","火","水","木","金","土") -> 水 | D15: 浅 | E15: 2週目：共感（本音・家族） | F15: D | G15: 再定義救済型 | H15: AIの回答が難しすぎる | I15: AIを「やさしい先生」に変えるひと言 | J15: tomoyo_pc_web（あなたのせいではない） | K15: AIの答えが難しく感じるのは、 あなたの理解力のせいではありません。 | L15: ChatGPTに「中学生にも分かるように」と一言足すだけで、 答えが別物になります。 | M15: カタカナだらけのAIの答えに、 そっとスマホを閉じたことはありませんか？ | N15: 1 | O15: 「プロンプト」「エンゲージメント」「マネタイズ」。 AIに聞いたのに、答えの意味が分からない。 もう一度聞くのも、なんだか情けない。 僕も最初はそうでした。 でも、AIはあなたが誰なのかを知りません。 だから「平均的な大人向け」の言葉で答えてくるんです。 あなたに合わせてもらう「ひと言」を足せばいい。 | P15: =CHOOSE(N15,K15,L15,M15)&CHAR(10)&CHAR(10)&O15 -> AIの答えが難しく感じるのは、 あなたの理解力のせいではありません。 「プロンプト」「エンゲージメント」「マネタイズ」。 AIに聞いたのに、答えの意味が分からない。 もう一度聞くのも、なんだか情けない。 僕も最初はそうでした。 でも、AIはあなたが誰なのかを知りません。 だから「平均的な大人向け」の言葉で答えてくるんです。 あなたに合わせてもらう「ひと言」を足せばいい。 | Q15: =LEN(P15) -> 190 | R15: 質問の最後に、これを付けてみてください。 ①「中学生にも分かる言葉で」 ②「カタカナ語は日本語に言い換えて」 ③「手順を番号付きで」 ④「1回に1つずつ教えて」 これだけで、AIは「やさしい先生」に変わります。 分からないまま閉じるのは、もったいない。 PC苦手な60代向けのAI質問テンプレは、プロフィールのNoteに。保存推奨です。 | S15: =LEN(R15) -> 172 | T15: AIの答えで分からなかった言葉は？ | U15: 保存・Note関心 | V15: =IF(OR(C15="土",C15="日"),"7:30","20:30") -> 20:30
A16: 11 | B16: =$B$2+A16-1 -> 46317 | C16: =CHOOSE(WEEKDAY(B16),"日","月","火","水","木","金","土") -> 木 | D16: 深 | E16: 2週目：共感（本音・家族） | F16: C | G16: 他者の一言→悔しさ→問い型 | H16: 家族にこれ以上心配をかけたくない／妻に申し訳ない | I16: 妻に言われた一言 | J16: saori.bihada.recipe（家族の一言→弱点→それでも） | K16: 「苦手な分野に行くから、成果が出ないんじゃない？」 妻に言われたこの一言が、ずっと胸に残っています。 | L16: 副業でいちばん支えてくれた人に、 いちばん心配をかけてきました。 | M16: 家族に反対される副業は、 だいたい「自分の苦手」に突っ込んでいます。 | N16: 1 | O16: 英語が苦手なのに、eBay輸出。 ずっと張り付けないのに、カメラ転売。 妻の言う通りでした。 それでも、AIの本を買ってきてくれたのは妻でした。 最初は反対していた相談会にも一緒に行って、 「この人なら信用できると思う」と言ってくれた。 今度こそ、苦手で戦わない。 妻に「やってよかったね」と言ってもらえるまで。 あなたの副業を、家族はどう見ていますか？ | P16: =CHOOSE(N16,K16,L16,M16)&CHAR(10)&CHAR(10)&O16 -> 「苦手な分野に行くから、成果が出ないんじゃない？」 妻に言われたこの一言が、ずっと胸に残っています。 英語が苦手なのに、eBay輸出。 ずっと張り付けないのに、カメラ転売。 妻の言う通りでした。 それでも、AIの本を買ってきてくれたのは妻でした。 最初は反対していた相談会にも一緒に行って、 「この人なら信用できると思う」と言ってくれた。 今度こそ、苦手で戦わない。 妻に「やってよかったね」と言ってもらえるまで。 あなたの副業を、家族はどう見ていますか？ | Q16: =LEN(P16) -> 233 | R16: 家族に応援される副業には、共通点があると思っています。 ・お金の上限が見えている ・何をしているか説明できる ・自分の得意に近い 僕が「苦手で戦わない副業」を選び直した方法は、 プロフィールのNoteに書きました。 同じように家族に心配をかけてきた方、 フォローして一緒に進みましょう。 | S16: =LEN(R16) -> 146 | T16: あなたの副業を、家族はどう見ていますか？ | U16: 共感・返信・フォロー | V16: =IF(OR(C16="土",C16="日"),"7:30","20:30") -> 20:30
A17: 12 | B17: =$B$2+A17-1 -> 46318 | C17: =CHOOSE(WEEKDAY(B17),"日","月","火","水","木","金","土") -> 金 | D17: 浅 | E17: 2週目：共感（本音・家族） | F17: B | G17: 断言リスト→引き型 | H17: スマホだけで副業できるか不安 | I17: 最初の30日はスマホ1台で十分 | J17: jin_kasegupro（リスト→問いで切る） | K17: 「パソコンがないと副業できない」は、 もう昔の話です。 | L17: 60代の副業、最初の30日はスマホ1台で十分です。 | M17: パソコンを買う前に、 まずスマホでやってほしいこと。 | N17: 2 | O17: スマホだけでできることは、こんなにあります。 ・Threadsへの投稿 ・ChatGPTアプリに声で相談 ・Noteの下書き ・投稿ネタのメモ ・反応の記録 高いパソコンも、難しいソフトもいりません。 では、パソコンがあると楽になるのはいつなのか。 | P17: =CHOOSE(N17,K17,L17,M17)&CHAR(10)&CHAR(10)&O17 -> 60代の副業、最初の30日はスマホ1台で十分です。 スマホだけでできることは、こんなにあります。 ・Threadsへの投稿 ・ChatGPTアプリに声で相談 ・Noteの下書き ・投稿ネタのメモ ・反応の記録 高いパソコンも、難しいソフトもいりません。 では、パソコンがあると楽になるのはいつなのか。 | Q17: =LEN(P17) -> 154 | R17: 答えは「長い文章をじっくり整える時」です。 Noteを1本の商品に仕上げる段階で、あると楽になります。 つまり最初の30日は、 スマホで「続ける習慣」を作ることが先。 道具から揃えるほど、副業は始まりません。 スマホ1台で始める30日の手順は、 プロフィールのNoteにまとめています。 | S17: =LEN(R17) -> 146 | T17: 副業はスマホ派？パソコン派？ | U17: 保存・ツリー遷移 | V17: =IF(OR(C17="土",C17="日"),"7:30","20:30") -> 20:30
... A35: 30 | B35: =$B$2+A35-1 -> 46336 | C35: =CHOOSE(WEEKDAY(B35),"日","月","火","水","木","金","土") -> 火 | D35: 深 | E35: 4週目：販売（Note導線強化） | F35: A | G35: 基本型（7ステップ・2投稿分割） | H35: 最後に一度、自分の力で稼ぎたい | I35: 30日間毎日投稿した60代のリアルな数字（実数を入れて投稿） | J35: yuko_insta_t（数字＋途中成果） | K35: 60代の副業迷子が、Threadsを30日間毎日投稿した結果。 数字を全部公開します。 | L35: 800万円の遠回りの「続き」は、 ここから書きます。 | M35: 30日前、フォロワーは【 】人でした。 | N35: 1 | O35: ・投稿数：30本 ・フォロワー：【開始時】人 →【30日目】人 ・一番読まれた投稿：【タイトル】 ・Noteの購入：【 】部 正直、うまくいかなかった日もありました。 それでも、毎日1本だけは出し続けた。 分かったのは、 60代の失敗談でも、ちゃんと誰かに届くということです。 | P35: =CHOOSE(N35,K35,L35,M35)&CHAR(10)&CHAR(10)&O35 -> 60代の副業迷子が、Threadsを30日間毎日投稿した結果。 数字を全部公開します。 ・投稿数：30本 ・フォロワー：【開始時】人 →【30日目】人 ・一番読まれた投稿：【タイトル】 ・Noteの購入：【 】部 正直、うまくいかなかった日もありました。 それでも、毎日1本だけは出し続けた。 分かったのは、 60代の失敗談でも、ちゃんと誰かに届くということです。 | Q35: =LEN(P35) -> 185 | R35: コメントで「自分も同じです」と言ってくれた方、 本当にありがとうございました。 この30日で集まった悩みと、僕の800万円分の遠回りを 「50代・60代のための副業迷子脱出ロードマップ」にまとめています。 次の30日は、初収益のその先へ。 これからも全部公開します。 フォローして、続きを一緒に見届けてください。 | S35: =LEN(R35) -> 158 | T35: この30日で一番役に立った投稿はどれでしたか？ | U35: Note購入・フォロー | V35: =IF(OR(C35="土",C35="日"),"7:30","20:30") -> 20:30

Sheet 効果測定
A1: 効果測定｜毎日の数字を記録して、勝ちパターンに寄せる
A2: 黄色セルに投稿の24時間後の数字を入力。率・売上は自動計算。プロフィール遷移・Noteクリックは各アプリのインサイト／Noteの管理画面で確認。
A3: Note価格（円） | B3: 980 | C3: ← ユーザー指定の初期価格（980〜2,980円の下限）。価格を変えたらここを更新
A5: Day | B5: 日付 | C5: 悩み区分 | D5: 構造型 | E5: 採用冒頭 | F5: 投稿テーマ | G5: 閲覧数 | H5: いいね | I5: 返信 | J5: 再投稿 | K5: 新規フォロー | L5: プロフィール閲覧 | M5: Noteクリック | N5: Note購入数 | O5: 反応率 | P5: プロフィール遷移率 | Q5: Note購入率（クリック比） | R5: 売上（円） | S5: 気づき（1行）
A6: 例 | C6: 浅 | D6: A | E6: 1 | F6: （記入例） | G6: 12000 | H6: 240 | I6: 35 | J6: 8 | K6: 40 | L6: 300 | M6: 25 | N6: 2 | O6: =IF(G6>0,(H6+I6+J6)/G6,"") -> 0.023583333 | P6: =IF(G6>0,L6/G6,"") -> 0.025 | Q6: =IF(M6>0,N6/M6,"") -> 0.08 | R6: =N6*$B$3 -> 1960 | S6: 記入例：この行は集計に含まれません
A7: =30日投稿スケジュール!A6 -> 1 | B7: =30日投稿スケジュール!B6 -> 46307 | C7: =30日投稿スケジュール!D6 -> 浅 | D7: =30日投稿スケジュール!F6 -> A | E7: =30日投稿スケジュール!N6 -> 1 | F7: =30日投稿スケジュール!I6 -> 副業と独立に約800万円使った60代の自己紹介（固定投稿にする） | O7: =IF(G7>0,(H7+I7+J7)/G7,"") | P7: =IF(G7>0,L7/G7,"") | Q7: =IF(M7>0,N7/M7,"") | R7: =N7*$B$3 -> 0
A8: =30日投稿スケジュール!A7 -> 2 | B8: =30日投稿スケジュール!B7 -> 46308 | C8: =30日投稿スケジュール!D7 -> 浅 | D8: =30日投稿スケジュール!F7 -> D | E8: =30日投稿スケジュール!N7 -> 2 | F8: =30日投稿スケジュール!I7 -> 小さい「ゃ」も打てなかった僕のPC入門 | O8: =IF(G8>0,(H8+I8+J8)/G8,"") | P8: =IF(G8>0,L8/G8,"") | Q8: =IF(M8>0,N8/M8,"") | R8: =N8*$B$3 -> 0
A9: =30日投稿スケジュール!A8 -> 3 | B9: =30日投稿スケジュール!B8 -> 46309 | C9: =30日投稿スケジュール!D8 -> 深 | D9: =30日投稿スケジュール!F8 -> C | E9: =30日投稿スケジュール!N8 -> 1 | F9: =30日投稿スケジュール!I8 -> 年齢で8社に断られた日 | O9: =IF(G9>0,(H9+I9+J9)/G9,"") | P9: =IF(G9>0,L9/G9,"") | Q9: =IF(M9>0,N9/M9,"") | R9: =N9*$B$3 -> 0
A10: =30日投稿スケジュール!A9 -> 4 | B10: =30日投稿スケジュール!B9 -> 46310 | C10: =30日投稿スケジュール!D9 -> 浅 | D10: =30日投稿スケジュール!F9 -> B | E10: =30日投稿スケジュール!N9 -> 1 | F10: =30日投稿スケジュール!I9 -> ChatGPTに最初にしてはいけない質問 | O10: =IF(G10>0,(H10+I10+J10)/G10,"") | P10: =IF(G10>0,L10/G10,"") | Q10: =IF(M10>0,N10/M10,"") | R10: =N10*$B$3 -> 0
A11: =30日投稿スケジュール!A10 -> 5 | B11: =30日投稿スケジュール!B10 -> 46311 | C11: =30日投稿スケジュール!D10 -> 浅 | D11: =30日投稿スケジュール!F10 -> A | E11: =30日投稿スケジュール!N10 -> 1 | F11: =30日投稿スケジュール!I10 -> コンサル6件受けて分かった、申し込む前のチェック | O11: =IF(G11>0,(H11+I11+J11)/G11,"") | P11: =IF(G11>0,L11/G11,"") | Q11: =IF(M11>0,N11/M11,"") | R11: =N11*$B$3 -> 0
A12: =30日投稿スケジュール!A11 -> 6 | B12: =30日投稿スケジュール!B11 -> 46312 | C12: =30日投稿スケジュール!D11 -> 浅 | D12: =30日投稿スケジュール!F11 -> D | E12: =30日投稿スケジュール!N11 -> 2 | F12: =30日投稿スケジュール!I11 -> 30年の日記と、60代のネタの掘り出し方 | O12: =IF(G12>0,(H12+I12+J12)/G12,"") | P12: =IF(G12>0,L12/G12,"") | Q12: =IF(M12>0,N12/M12,"") | R12: =N12*$B$3 -> 0
A13: =30日投稿スケジュール!A12 -> 7 | B13: =30日投稿スケジュール!B12 -> 46313 | C13: =30日投稿スケジュール!D12 -> 浅 | D13: =30日投稿スケジュール!F12 -> E | E13: =30日投稿スケジュール!N12 -> 1 | F13: =30日投稿スケジュール!I12 -> 副業、何回やめましたか？（参加型） | O13: =IF(G13>0,(H13+I13+J13)/G13,"") | P13: =IF(G13>0,L13/G13,"") | Q13: =IF(M13>0,N13/M13,"") | R13: =N13*$B$3 -> 0
A14: =30日投稿スケジュール!A13 -> 8 | B14: =30日投稿スケジュール!B13 -> 46314 | C14: =30日投稿スケジュール!D13 -> 深 | D14: =30日投稿スケジュール!F13 -> A | E14: =30日投稿スケジュール!N13 -> 1 | F14: =30日投稿スケジュール!I13 -> 怖いのはお金より「自分にがっかりすること」 | O14: =IF(G14>0,(H14+I14+J14)/G14,"") | P14: =IF(G14>0,L14/G14,"") | Q14: =IF(M14>0,N14/M14,"") | R14: =N14*$B$3 -> 0
A15: =30日投稿スケジュール!A14 -> 9 | B15: =30日投稿スケジュール!B14 -> 46315 | C15: =30日投稿スケジュール!D14 -> 浅 | D15: =30日投稿スケジュール!F14 -> G | E15: =30日投稿スケジュール!N14 -> 2 | F15: =30日投稿スケジュール!I14 -> 時間を作らず、習慣に「くっつける」 | O15: =IF(G15>0,(H15+I15+J15)/G15,"") | P15: =IF(G15>0,L15/G15,"") | Q15: =IF(M15>0,N15/M15,"") | R15: =N15*$B$3 -> 0
A16: =30日投稿スケジュール!A15 -> 10 | B16: =30日投稿スケジュール!B15 -> 46316 | C16: =30日投稿スケジュール!D15 -> 浅 | D16: =30日投稿スケジュール!F15 -> D | E16: =30日投稿スケジュール!N15 -> 1 | F16: =30日投稿スケジュール!I15 -> AIを「やさしい先生」に変えるひと言 | O16: =IF(G16>0,(H16+I16+J16)/G16,"") | P16: =IF(G16>0,L16/G16,"") | Q16: =IF(M16>0,N16/M16,"") | R16: =N16*$B$3 -> 0
A17: =30日投稿スケジュール!A16 -> 11 | B17: =30日投稿スケジュール!B16 -> 46317 | C17: =30日投稿スケジュール!D16 -> 深 | D17: =30日投稿スケジュール!F16 -> C | E17: =30日投稿スケジュール!N16 -> 1 | F17: =30日投稿スケジュール!I16 -> 妻に言われた一言 | O17: =IF(G17>0,(H17+I17+J17)/G17,"") | P17: =IF(G17>0,L17/G17,"") | Q17: =IF(M17>0,N17/M17,"") | R17: =N17*$B$3 -> 0
A18: =30日投稿スケジュール!A17 -> 12 | B18: =30日投稿スケジュール!B17 -> 46318 | C18: =30日投稿スケジュール!D17 -> 浅 | D18: =30日投稿スケジュール!F17 -> B | E18: =30日投稿スケジュール!N17 -> 2 | F18: =30日投稿スケジュール!I17 -> 最初の30日はスマホ1台で十分 | O18: =IF(G18>0,(H18+I18+J18)/G18,"") | P18: =IF(G18>0,L18/G18,"") | Q18: =IF(M18>0,N18/M18,"") | R18: =N18*$B$3 -> 0
... A36: =30日投稿スケジュール!A35 -> 30 | B36: =30日投稿スケジュール!B35 -> 46336 | C36: =30日投稿スケジュール!D35 -> 深 | D36: =30日投稿スケジュール!F35 -> A | E36: =30日投稿スケジュール!N35 -> 1 | F36: =30日投稿スケジュール!I35 -> 30日間毎日投稿した60代のリアルな数字（実数を入れて投稿） | O36: =IF(G36>0,(H36+I36+J36)/G36,"") | P36: =IF(G36>0,L36/G36,"") | Q36: =IF(M36>0,N36/M36,"") | R36: =N36*$B$3 -> 0
A37: 合計 | G37: =SUM(G7:G36) -> 0 | H37: =SUM(H7:H36) -> 0 | I37: =SUM(I7:I36) -> 0 | J37: =SUM(J7:J36) -> 0 | K37: =SUM(K7:K36) -> 0 | L37: =SUM(L7:L36) -> 0 | M37: =SUM(M7:M36) -> 0 | N37: =SUM(N7:N36) -> 0 | O37: =IF(G37>0,(H37+I37+J37)/G37,"") | P37: =IF(G37>0,L37/G37,"") | Q37: =IF(M37>0,N37/M37,"") | R37: =SUM(R7:R36) -> 0
A39: ■ 型・悩み区分ごとの平均（どの型が伸びるかを判断）
A40: 区分 | B40: 投稿数 | C40: 平均閲覧数 | D40: 平均返信 | E40: 平均プロフィール遷移率 | F40: Note購入数合計
A41: 悩み：浅 | B41: =COUNTIF($C$7:$C$36,$G41) -> 21 | C41: =IFERROR(AVERAGEIFS($G$7:$G$36,$C$7:$C$36,$G41,$G$7:$G$36,">0"),"未入力") -> 未入力 | D41: =IFERROR(AVERAGEIFS($I$7:$I$36,$C$7:$C$36,$G41,$G$7:$G$36,">0"),"未入力") -> 未入力 | E41: =IFERROR(SUMIFS($L$7:$L$36,$C$7:$C$36,$G41)/SUMIFS($G$7:$G$36,$C$7:$C$36,$G41),"未入力") -> 未入力 | F41: =SUMIFS($N$7:$N$36,$C$7:$C$36,$G41) -> 0 | G41: 浅
A42: 悩み：深 | B42: =COUNTIF($C$7:$C$36,$G42) -> 9 | C42: =IFERROR(AVERAGEIFS($G$7:$G$36,$C$7:$C$36,$G42,$G$7:$G$36,">0"),"未入力") -> 未入力 | D42: =IFERROR(AVERAGEIFS($I$7:$I$36,$C$7:$C$36,$G42,$G$7:$G$36,">0"),"未入力") -> 未入力 | E42: =IFERROR(SUMIFS($L$7:$L$36,$C$7:$C$36,$G42)/SUMIFS($G$7:$G$36,$C$7:$C$36,$G42),"未入力") -> 未入力 | F42: =SUMIFS($N$7:$N$36,$C$7:$C$36,$G42) -> 0 | G42: 深
A43: 型A：基本型（7ステップ・2投稿分割） | B43: =COUNTIF($D$7:$D$36,$G43) -> 8 | C43: =IFERROR(AVERAGEIFS($G$7:$G$36,$D$7:$D$36,$G43,$G$7:$G$36,">0"),"未入力") -> 未入力 | D43: =IFERROR(AVERAGEIFS($I$7:$I$36,$D$7:$D$36,$G43,$G$7:$G$36,">0"),"未入力") -> 未入力 | E43: =IFERROR(SUMIFS($L$7:$L$36,$D$7:$D$36,$G43)/SUMIFS($G$7:$G$36,$D$7:$D$36,$G43),"未入力") -> 未入力 | F43: =SUMIFS($N$7:$N$36,$D$7:$D$36,$G43) -> 0 | G43: A
A44: 型B：断言リスト→引き型 | B44: =COUNTIF($D$7:$D$36,$G44) -> 5 | C44: =IFERROR(AVERAGEIFS($G$7:$G$36,$D$7:$D$36,$G44,$G$7:$G$36,">0"),"未入力") -> 未入力 | D44: =IFERROR(AVERAGEIFS($I$7:$I$36,$D$7:$D$36,$G44,$G$7:$G$36,">0"),"未入力") -> 未入力 | E44: =IFERROR(SUMIFS($L$7:$L$36,$D$7:$D$36,$G44)/SUMIFS($G$7:$G$36,$D$7:$D$36,$G44),"未入力") -> 未入力 | F44: =SUMIFS($N$7:$N$36,$D$7:$D$36,$G44) -> 0 | G44: B
A45: 型C：他者の一言→悔しさ→問い型 | B45: =COUNTIF($D$7:$D$36,$G45) -> 3 | C45: =IFERROR(AVERAGEIFS($G$7:$G$36,$D$7:$D$36,$G45,$G$7:$G$36,">0"),"未入力") -> 未入力 | D45: =IFERROR(AVERAGEIFS($I$7:$I$36,$D$7:$D$36,$G45,$G$7:$G$36,">0"),"未入力") -> 未入力 | E45: =IFERROR(SUMIFS($L$7:$L$36,$D$7:$D$36,$G45)/SUMIFS($G$7:$G$36,$D$7:$D$36,$G45),"未入力") -> 未入力 | F45: =SUMIFS($N$7:$N$36,$D$7:$D$36,$G45) -> 0 | G45: C
A46: 型D：再定義救済型 | B46: =COUNTIF($D$7:$D$36,$G46) -> 8 | C46: =IFERROR(AVERAGEIFS($G$7:$G$36,$D$7:$D$36,$G46,$G$7:$G$36,">0"),"未入力") -> 未入力 | D46: =IFERROR(AVERAGEIFS($I$7:$I$36,$D$7:$D$36,$G46,$G$7:$G$36,">0"),"未入力") -> 未入力 | E46: =IFERROR(SUMIFS($L$7:$L$36,$D$7:$D$36,$G46)/SUMIFS($G$7:$G$36,$D$7:$D$36,$G46),"未入力") -> 未入力 | F46: =SUMIFS($N$7:$N$36,$D$7:$D$36,$G46) -> 0 | G46: D
A47: 型E：告白＋「私だけ？」型 | B47: =COUNTIF($D$7:$D$36,$G47) -> 3 | C47: =IFERROR(AVERAGEIFS($G$7:$G$36,$D$7:$D$36,$G47,$G$7:$G$36,">0"),"未入力") -> 未入力 | D47: =IFERROR(AVERAGEIFS($I$7:$I$36,$D$7:$D$36,$G47,$G$7:$G$36,">0"),"未入力") -> 未入力 | E47: =IFERROR(SUMIFS($L$7:$L$36,$D$7:$D$36,$G47)/SUMIFS($G$7:$G$36,$D$7:$D$36,$G47),"未入力") -> 未入力 | F47: =SUMIFS($N$7:$N$36,$D$7:$D$36,$G47) -> 0 | G47: E
A48: 型F：一言引用→余韻型 | B48: =COUNTIF($D$7:$D$36,$G48) -> 1 | C48: =IFERROR(AVERAGEIFS($G$7:$G$36,$D$7:$D$36,$G48,$G$7:$G$36,">0"),"未入力") -> 未入力 | D48: =IFERROR(AVERAGEIFS($I$7:$I$36,$D$7:$D$36,$G48,$G$7:$G$36,">0"),"未入力") -> 未入力 | E48: =IFERROR(SUMIFS($L$7:$L$36,$D$7:$D$36,$G48)/SUMIFS($G$7:$G$36,$D$7:$D$36,$G48),"未入力") -> 未入力 | F48: =SUMIFS($N$7:$N$36,$D$7:$D$36,$G48) -> 0 | G48: F
A49: 型G：一行の根拠→具体3つ→結論型 | B49: =COUNTIF($D$7:$D$36,$G49) -> 2 | C49: =IFERROR(AVERAGEIFS($G$7:$G$36,$D$7:$D$36,$G49,$G$7:$G$36,">0"),"未入力") -> 未入力 | D49: =IFERROR(AVERAGEIFS($I$7:$I$36,$D$7:$D$36,$G49,$G$7:$G$36,">0"),"未入力") -> 未入力 | E49: =IFERROR(SUMIFS($L$7:$L$36,$D$7:$D$36,$G49)/SUMIFS($G$7:$G$36,$D$7:$D$36,$G49),"未入力") -> 未入力 | F49: =SUMIFS($N$7:$N$36,$D$7:$D$36,$G49) -> 0 | G49: G
A51: 判断の目安：プロフィール遷移率が高い型を4週目以降に増やす／返信が多い型はNote導線より会話を優先／閲覧は多いが遷移が低い投稿は、ツリー最後の導線文を見直す。
